telemetrise/__init__.py
telemetrise/telemetrise.py
telemetrise-0.0.8.dist-info/DESCRIPTION.rst
telemetrise-0.0.8.dist-info/METADATA
telemetrise-0.0.8.dist-info/RECORD
telemetrise-0.0.8.dist-info/WHEEL
telemetrise-0.0.8.dist-info/entry_points.txt
telemetrise-0.0.8.dist-info/metadata.json
telemetrise-0.0.8.dist-info/top_level.txt
