Metadata-Version: 2.0
Name: telemetrise
Version: 0.0.8
Summary: Telemetry on any command
Home-page: UNKNOWN
Author: Ian Miell
Author-email: ian.miell@gmail.com
License: UNKNOWN
Platform: UNKNOWN
Requires-Dist: curtsies
Requires-Dist: pexpect
